{
  "^agora::media::(.*)": "$1",
  "^Optional<(.*)>": "$1",
  "^util::(.*)": "$1",
  "^agora::(.*)": "$1",
  "^rtc::(.*)": "$1",
  "^media::(.*)": "$1",
  "^base::(.*)": "$1",
  "^media::base::(.*)": "$1",
  "^agora::media::base::(.*)": "$1",
  "^agora::base::(.*)": "$1",
  "^agora::rtc::(.*)": "$1",
  "^agora_refptr<agora::rtc::(.*)>": "$1",
  "^agora::util::(.*)": "$1",
  "^(.*)::(.*)": "$2",
  "VideoCompositingLayout::Region": "Region[]",
  "ChannelMediaInfo*": "ChannelMediaInfo[]",
  "ContentInspectModule*": "ContentInspectModule[]",
  "^ExternalVideoFrame::(.*)": "$1",
  "^IAudioFrameObserverBase::(.*)": "$1",

  "^AString$": "string",
  "^user_id_t$": "string",
  "^view_t$": "number",
  "^uid_t$": "number",
  "^track_id_t$": "number",
  "^video_track_id_t$": "number",
  "^conn_id_t$": "number",

  "^size_t$": "number",

  "^const char \\*$": "string",
  "^const char*$": "string",
  "^unsigned int$": "number",
  "^unsigned short$": "number",
  "^unsigned char$": "Uint8Array",
  "^char$": "string",

  "^ushort$": "number",

  "^long long$": "number",
  "^ulong$": "number",
  "^long$": "number",

  "^uint8_t$": "number",
  "^uint32_t$": "number",
  "^uint64_t$": "number",
  "^uint16_t$": "number",
  "^uint$": "number",

  "^int64_t$": "number",
  "^int32_t$": "number",
  "^int16_t$": "number",
  "^int$": "number",

  "^float$": "number",
  "^double$": "number",

  "^bool$": "boolean"
}
